tsim/__init__.py
tsim/main.py
tsim-0.1.0.dist-info/licenses/LICENSE
tsim-0.1.0.dist-info/METADATA
tsim-0.1.0.dist-info/WHEEL
tsim-0.1.0.dist-info/top_level.txt
tsim-0.1.0.dist-info/RECORD
