Metadata-Version: 2.4
Name: tsim
Version: 0.1.0
Summary: A lightweight library for quantifying the similarity between two strings
Author-email: Sanyam Asthana <sanyam.asthana@gmail.com>
License-File: LICENSE
Dynamic: license-file
